example_package/__init__.py
example_package/example.py
jsoncsvtxt-0.0.1.dist-info/LICENSE
jsoncsvtxt-0.0.1.dist-info/METADATA
jsoncsvtxt-0.0.1.dist-info/WHEEL
jsoncsvtxt-0.0.1.dist-info/top_level.txt
jsoncsvtxt-0.0.1.dist-info/RECORD
