Metadata-Version: 2.1
Name: jsoncsvtxt
Version: 0.0.1
Summary: A simple module to create/read/write/truncate...a json or csv or txt file using python
Home-page: https://github.com/pypa/sampleproject
Author: mohamed zarra
Author-email: zarramohamed.05@gmail.com
Project-URL: Bug Tracker, https://github.com/pypa/sampleproject/issues
Classifier: Programming Language :: Python :: 3
Classifier: License :: OSI Approved :: MIT License
Classifier: Operating System :: OS Independent
Requires-Python: >=3.6
License-File: LICENSE
